{"allContent":{"docusaurus-plugin-css-cascade-layers":{},"docusaurus-plugin-content-docs":{"default":{"loadedVersions":[{"versionName":"current","label":"Next","banner":null,"badge":false,"noIndex":false,"className":"docs-version-current","path":"/docs","tagsPath":"/docs/tags","isLast":true,"routePriority":-1,"sidebarFilePath":"/Users/ishimototatsuya/Documents/works/inhouse/garaku-frontend/docs-site/sidebars.ts","contentPath":"/Users/ishimototatsuya/Documents/works/inhouse/garaku-frontend/docs-site/docs","docs":[{"id":"admin/admin-shift","title":"シフトを管理する","description":"このページでは、シフトを確認、調整するための基本運用を説明します。","source":"@site/docs/admin/admin-shift.md","sourceDirName":"admin","slug":"/admin/admin-shift","permalink":"/docs/admin/admin-shift","draft":false,"unlisted":false,"tags":[],"version":"current","sidebarPosition":7,"frontMatter":{"sidebar_position":7},"sidebar":"mainSidebar","previous":{"title":"ダッシュボードを確認する","permalink":"/docs/admin/dashboard"},"next":{"title":"シフト計画を作成する","permalink":"/docs/admin/shift-plan"}},{"id":"admin/attendance-management","title":"勤怠を管理する","description":"このページでは、管理者が日々の勤怠状況を確認し、要確認データを解消する手順を説明します。","source":"@site/docs/admin/attendance-management.md","sourceDirName":"admin","slug":"/admin/attendance-management","permalink":"/docs/admin/attendance-management","draft":false,"unlisted":false,"tags":[],"version":"current","sidebarPosition":4,"frontMatter":{"sidebar_position":4},"sidebar":"mainSidebar","previous":{"title":"シフト計画を作成する","permalink":"/docs/admin/shift-plan"},"next":{"title":"日報を管理する","permalink":"/docs/admin/daily-report"}},{"id":"admin/attendances","title":"勤怠一覧を確認する","description":"このページでは、勤怠一覧で優先度をつけて対応する手順を説明します。","source":"@site/docs/admin/attendances.md","sourceDirName":"admin","slug":"/admin/attendances","permalink":"/docs/admin/attendances","draft":false,"unlisted":false,"tags":[],"version":"current","sidebarPosition":5,"frontMatter":{"sidebar_position":5},"sidebar":"mainSidebar","previous":{"title":"日報を管理する","permalink":"/docs/admin/daily-report"},"next":{"title":"申請を承認する","permalink":"/docs/admin/request-approval"}},{"id":"admin/daily-report","title":"日報を管理する","description":"このページでは、スタッフの日報を確認して、未対応を減らす手順を説明します。","source":"@site/docs/admin/daily-report.md","sourceDirName":"admin","slug":"/admin/daily-report","permalink":"/docs/admin/daily-report","draft":false,"unlisted":false,"tags":[],"version":"current","sidebarPosition":6,"frontMatter":{"sidebar_position":6},"sidebar":"mainSidebar","previous":{"title":"勤怠を管理する","permalink":"/docs/admin/attendance-management"},"next":{"title":"勤怠一覧を確認する","permalink":"/docs/admin/attendances"}},{"id":"admin/dashboard","title":"ダッシュボードを確認する","description":"このページでは、管理画面ダッシュボード（/admin）でその日の優先対応を素早く判断するための見方を説明します。","source":"@site/docs/admin/dashboard.md","sourceDirName":"admin","slug":"/admin/dashboard","permalink":"/docs/admin/dashboard","draft":false,"unlisted":false,"tags":[],"version":"current","sidebarPosition":3,"frontMatter":{"sidebar_position":3},"sidebar":"mainSidebar","previous":{"title":"画面遷移マップ（管理者向け）","permalink":"/docs/admin/navigation-map"},"next":{"title":"シフトを管理する","permalink":"/docs/admin/admin-shift"}},{"id":"admin/faq","title":"よくある質問","description":"Q. 管理者はどこで申請を確認できますか？","source":"@site/docs/admin/faq.md","sourceDirName":"admin","slug":"/admin/faq","permalink":"/docs/admin/faq","draft":false,"unlisted":false,"tags":[],"version":"current","sidebarPosition":5,"frontMatter":{"sidebar_position":5},"sidebar":"mainSidebar","previous":{"title":"スタッフを管理する","permalink":"/docs/admin/staff-management"},"next":{"title":"開発者向けドキュメント","permalink":"/docs/developer/overview"}},{"id":"admin/navigation-map","title":"画面遷移マップ（管理者向け）","description":"迷ったときに、目的から行き先を決めるためのページです。","source":"@site/docs/admin/navigation-map.md","sourceDirName":"admin","slug":"/admin/navigation-map","permalink":"/docs/admin/navigation-map","draft":false,"unlisted":false,"tags":[],"version":"current","sidebarPosition":2,"frontMatter":{"sidebar_position":2},"sidebar":"mainSidebar","previous":{"title":"管理者向けドキュメント","permalink":"/docs/admin/overview"},"next":{"title":"ダッシュボードを確認する","permalink":"/docs/admin/dashboard"}},{"id":"admin/operation-logs","title":"操作ログを確認する","description":"このページでは、いつ、誰が、どの操作をしたかを確認する手順を説明します。","source":"@site/docs/admin/operation-logs.md","sourceDirName":"admin","slug":"/admin/operation-logs","permalink":"/docs/admin/operation-logs","draft":false,"unlisted":false,"tags":[],"version":"current","sidebarPosition":7,"frontMatter":{"sidebar_position":7},"sidebar":"mainSidebar","previous":{"title":"ワークフロー申請を管理する","permalink":"/docs/admin/workflow"},"next":{"title":"設定画面を管理する","permalink":"/docs/admin/settings-management"}},{"id":"admin/overview","title":"管理者向けドキュメント","description":"このセクションは、管理者の日常運用に必要な操作をまとめた案内です。","source":"@site/docs/admin/overview.md","sourceDirName":"admin","slug":"/admin/overview","permalink":"/docs/admin/overview","draft":false,"unlisted":false,"tags":[],"version":"current","sidebarPosition":1,"frontMatter":{"sidebar_position":1},"sidebar":"mainSidebar","previous":{"title":"よくある質問","permalink":"/docs/staff/faq"},"next":{"title":"画面遷移マップ（管理者向け）","permalink":"/docs/admin/navigation-map"}},{"id":"admin/request-approval","title":"申請を承認する","description":"このページでは、管理者が勤怠修正申請を確認し、承認・却下する手順を説明します。","source":"@site/docs/admin/request-approval.md","sourceDirName":"admin","slug":"/admin/request-approval","permalink":"/docs/admin/request-approval","draft":false,"unlisted":false,"tags":[],"version":"current","sidebarPosition":6,"frontMatter":{"sidebar_position":6},"sidebar":"mainSidebar","previous":{"title":"勤怠一覧を確認する","permalink":"/docs/admin/attendances"},"next":{"title":"ワークフロー申請を管理する","permalink":"/docs/admin/workflow"}},{"id":"admin/settings-management","title":"設定画面を管理する","description":"このページでは、管理者が設定画面で何を見直し、変更後にどこを確認すればよいかを説明します。","source":"@site/docs/admin/settings-management.md","sourceDirName":"admin","slug":"/admin/settings-management","permalink":"/docs/admin/settings-management","draft":false,"unlisted":false,"tags":[],"version":"current","sidebarPosition":10,"frontMatter":{"sidebar_position":10},"sidebar":"mainSidebar","previous":{"title":"操作ログを確認する","permalink":"/docs/admin/operation-logs"},"next":{"title":"スタッフを管理する","permalink":"/docs/admin/staff-management"}},{"id":"admin/shift-plan","title":"シフト計画を作成する","description":"このページでは、年間のシフト計画を作成、更新するための基本運用を説明します。","source":"@site/docs/admin/shift-plan.md","sourceDirName":"admin","slug":"/admin/shift-plan","permalink":"/docs/admin/shift-plan","draft":false,"unlisted":false,"tags":[],"version":"current","sidebarPosition":8,"frontMatter":{"sidebar_position":8},"sidebar":"mainSidebar","previous":{"title":"シフトを管理する","permalink":"/docs/admin/admin-shift"},"next":{"title":"勤怠を管理する","permalink":"/docs/admin/attendance-management"}},{"id":"admin/staff-management","title":"スタッフを管理する","description":"このページでは、スタッフアカウントを管理する手順を説明します。","source":"@site/docs/admin/staff-management.md","sourceDirName":"admin","slug":"/admin/staff-management","permalink":"/docs/admin/staff-management","draft":false,"unlisted":false,"tags":[],"version":"current","sidebarPosition":7,"frontMatter":{"sidebar_position":7},"sidebar":"mainSidebar","previous":{"title":"設定画面を管理する","permalink":"/docs/admin/settings-management"},"next":{"title":"よくある質問","permalink":"/docs/admin/faq"}},{"id":"admin/workflow","title":"ワークフロー申請を管理する","description":"このページでは、管理者がワークフロー画面で申請を確認し、承認・却下を行う手順を説明します。","source":"@site/docs/admin/workflow.md","sourceDirName":"admin","slug":"/admin/workflow","permalink":"/docs/admin/workflow","draft":false,"unlisted":false,"tags":[],"version":"current","sidebarPosition":7,"frontMatter":{"sidebar_position":7},"sidebar":"mainSidebar","previous":{"title":"申請を承認する","permalink":"/docs/admin/request-approval"},"next":{"title":"操作ログを確認する","permalink":"/docs/admin/operation-logs"}},{"id":"developer/attendance-error-list-display","title":"打刻エラー一覧の表示仕様","description":"/attendance/list のデスクトップ画面に表示される「打刻エラー一覧」と、モバイル画面の警告アラートの表示条件を定義する。","source":"@site/docs/developer/attendance-error-list-display.md","sourceDirName":"developer","slug":"/developer/attendance-error-list-display","permalink":"/docs/developer/attendance-error-list-display","draft":false,"unlisted":false,"tags":[],"version":"current","sidebarPosition":3,"frontMatter":{"sidebar_position":3},"sidebar":"mainSidebar","previous":{"title":"勤怠管理対象フラグ仕様","permalink":"/docs/developer/attendance-management-enabled"},"next":{"title":"勤怠ステータス判定ロジック","permalink":"/docs/developer/attendance-status-determination"}},{"id":"developer/attendance-management-enabled","title":"勤怠管理対象フラグ仕様","description":"このページは、スタッフ単位の勤怠管理対象フラグ（attendanceManagementEnabled）の仕様をまとめる。","source":"@site/docs/developer/attendance-management-enabled.md","sourceDirName":"developer","slug":"/developer/attendance-management-enabled","permalink":"/docs/developer/attendance-management-enabled","draft":false,"unlisted":false,"tags":[],"version":"current","sidebarPosition":2,"frontMatter":{"sidebar_position":2},"sidebar":"mainSidebar","previous":{"title":"セットアップ","permalink":"/docs/developer/getting-started/setup"},"next":{"title":"打刻エラー一覧の表示仕様","permalink":"/docs/developer/attendance-error-list-display"}},{"id":"developer/attendance-status-determination","title":"勤怠ステータス判定ロジック","description":"スタッフの 1 日分の勤怠ステータスを返す中核ライブラリの仕様を定義する。","source":"@site/docs/developer/attendance-status-determination.md","sourceDirName":"developer","slug":"/developer/attendance-status-determination","permalink":"/docs/developer/attendance-status-determination","draft":false,"unlisted":false,"tags":[],"version":"current","sidebarPosition":4,"frontMatter":{"sidebar_position":4},"sidebar":"mainSidebar","previous":{"title":"打刻エラー一覧の表示仕様","permalink":"/docs/developer/attendance-error-list-display"}},{"id":"developer/getting-started/setup","title":"セットアップ","description":"このページは、garaku-frontend の開発を始めるための最小セットアップ手順です。","source":"@site/docs/developer/getting-started/setup.md","sourceDirName":"developer/getting-started","slug":"/developer/getting-started/setup","permalink":"/docs/developer/getting-started/setup","draft":false,"unlisted":false,"tags":[],"version":"current","sidebarPosition":1,"frontMatter":{"sidebar_position":1},"sidebar":"mainSidebar","previous":{"title":"開発者向けドキュメント","permalink":"/docs/developer/overview"},"next":{"title":"勤怠管理対象フラグ仕様","permalink":"/docs/developer/attendance-management-enabled"}},{"id":"developer/overview","title":"開発者向けドキュメント","description":"このセクションは、garaku-frontend の開発に参加するメンバー向けです。","source":"@site/docs/developer/overview.md","sourceDirName":"developer","slug":"/developer/overview","permalink":"/docs/developer/overview","draft":false,"unlisted":false,"tags":[],"version":"current","sidebarPosition":1,"frontMatter":{"sidebar_position":1},"sidebar":"mainSidebar","previous":{"title":"よくある質問","permalink":"/docs/admin/faq"},"next":{"title":"セットアップ","permalink":"/docs/developer/getting-started/setup"}},{"id":"intro","title":"はじめに","description":"このサイトは、garaku-frontend のドキュメントポータルです。","source":"@site/docs/intro.md","sourceDirName":".","slug":"/intro","permalink":"/docs/intro","draft":false,"unlisted":false,"tags":[],"version":"current","sidebarPosition":1,"frontMatter":{"sidebar_position":1},"sidebar":"mainSidebar","next":{"title":"スタッフ向けドキュメント","permalink":"/docs/staff/overview"}},{"id":"staff/attendance-check","title":"勤怠を確認する","description":"このページでは、打刻後の勤怠確認と、必要時の修正申請の流れを説明します。","source":"@site/docs/staff/attendance-check.md","sourceDirName":"staff","slug":"/staff/attendance-check","permalink":"/docs/staff/attendance-check","draft":false,"unlisted":false,"tags":[],"version":"current","sidebarPosition":4,"frontMatter":{"sidebar_position":4},"sidebar":"mainSidebar","previous":{"title":"シフトを確認・編集する","permalink":"/docs/staff/shift"},"next":{"title":"ワークフロー申請を操作する","permalink":"/docs/staff/workflow"}},{"id":"staff/attendance-edit","title":"勤怠を修正する","description":"このページでは、勤怠編集画面で打刻ミスや休憩漏れを修正し、申請する手順を説明します。","source":"@site/docs/staff/attendance-edit.md","sourceDirName":"staff","slug":"/staff/attendance-edit","permalink":"/docs/staff/attendance-edit","draft":false,"unlisted":false,"tags":[],"version":"current","sidebarPosition":5,"frontMatter":{"sidebar_position":5},"sidebar":"mainSidebar","previous":{"title":"ワークフロー申請を操作する","permalink":"/docs/staff/workflow"},"next":{"title":"日報を記録する","permalink":"/docs/staff/attendance-report"}},{"id":"staff/attendance-report","title":"日報を記録する","description":"このページでは、日報画面でその日の業務内容を記録し、提出する手順を説明します。","source":"@site/docs/staff/attendance-report.md","sourceDirName":"staff","slug":"/staff/attendance-report","permalink":"/docs/staff/attendance-report","draft":false,"unlisted":false,"tags":[],"version":"current","sidebarPosition":6,"frontMatter":{"sidebar_position":6},"sidebar":"mainSidebar","previous":{"title":"勤怠を修正する","permalink":"/docs/staff/attendance-edit"},"next":{"title":"申請を確認する","permalink":"/docs/staff/request-check"}},{"id":"staff/basic-operations","title":"基本操作","description":"このページでは、日常業務でよく使う操作を、最短で確認できるようにまとめます。","source":"@site/docs/staff/basic-operations.md","sourceDirName":"staff","slug":"/staff/basic-operations","permalink":"/docs/staff/basic-operations","draft":false,"unlisted":false,"tags":[],"version":"current","sidebarPosition":2,"frontMatter":{"sidebar_position":2},"sidebar":"mainSidebar","previous":{"title":"画面遷移マップ（スタッフ向け）","permalink":"/docs/staff/navigation-map"},"next":{"title":"出退勤を打刻する","permalink":"/docs/staff/time-recording"}},{"id":"staff/dashboard","title":"打刻ダッシュボードを確認する","description":"このページでは、打刻画面の右側に表示される「打刻ダッシュボード」で何を確認できるかを説明します。","source":"@site/docs/staff/dashboard.md","sourceDirName":"staff","slug":"/staff/dashboard","permalink":"/docs/staff/dashboard","draft":false,"unlisted":false,"tags":[],"version":"current","sidebarPosition":3,"frontMatter":{"sidebar_position":3},"sidebar":"mainSidebar","previous":{"title":"出退勤を打刻する","permalink":"/docs/staff/time-recording"},"next":{"title":"シフトを確認・編集する","permalink":"/docs/staff/shift"}},{"id":"staff/faq","title":"よくある質問","description":"Q. どこから始めればよいですか？","source":"@site/docs/staff/faq.md","sourceDirName":"staff","slug":"/staff/faq","permalink":"/docs/staff/faq","draft":false,"unlisted":false,"tags":[],"version":"current","sidebarPosition":3,"frontMatter":{"sidebar_position":3},"sidebar":"mainSidebar","previous":{"title":"申請を確認する","permalink":"/docs/staff/request-check"},"next":{"title":"管理者向けドキュメント","permalink":"/docs/admin/overview"}},{"id":"staff/navigation-map","title":"画面遷移マップ（スタッフ向け）","description":"迷ったときに、目的から行き先を決めるためのページです。","source":"@site/docs/staff/navigation-map.md","sourceDirName":"staff","slug":"/staff/navigation-map","permalink":"/docs/staff/navigation-map","draft":false,"unlisted":false,"tags":[],"version":"current","sidebarPosition":2,"frontMatter":{"sidebar_position":2},"sidebar":"mainSidebar","previous":{"title":"スタッフ向けドキュメント","permalink":"/docs/staff/overview"},"next":{"title":"基本操作","permalink":"/docs/staff/basic-operations"}},{"id":"staff/overview","title":"スタッフ向けドキュメント","description":"このセクションは、日々の勤怠作業を行うスタッフ向けの案内です。","source":"@site/docs/staff/overview.md","sourceDirName":"staff","slug":"/staff/overview","permalink":"/docs/staff/overview","draft":false,"unlisted":false,"tags":[],"version":"current","sidebarPosition":1,"frontMatter":{"sidebar_position":1},"sidebar":"mainSidebar","previous":{"title":"はじめに","permalink":"/docs/intro"},"next":{"title":"画面遷移マップ（スタッフ向け）","permalink":"/docs/staff/navigation-map"}},{"id":"staff/request-check","title":"申請を確認する","description":"このページでは、勤怠修正申請の確認手順を説明します。","source":"@site/docs/staff/request-check.md","sourceDirName":"staff","slug":"/staff/request-check","permalink":"/docs/staff/request-check","draft":false,"unlisted":false,"tags":[],"version":"current","sidebarPosition":5,"frontMatter":{"sidebar_position":5},"sidebar":"mainSidebar","previous":{"title":"日報を記録する","permalink":"/docs/staff/attendance-report"},"next":{"title":"よくある質問","permalink":"/docs/staff/faq"}},{"id":"staff/shift","title":"シフトを確認・編集する","description":"このページでは、シフトの確認と編集の基本操作を説明します。","source":"@site/docs/staff/shift.md","sourceDirName":"staff","slug":"/staff/shift","permalink":"/docs/staff/shift","draft":false,"unlisted":false,"tags":[],"version":"current","sidebarPosition":5,"frontMatter":{"sidebar_position":5},"sidebar":"mainSidebar","previous":{"title":"打刻ダッシュボードを確認する","permalink":"/docs/staff/dashboard"},"next":{"title":"勤怠を確認する","permalink":"/docs/staff/attendance-check"}},{"id":"staff/time-recording","title":"出退勤を打刻する","description":"このページでは、勤務開始から勤務終了までの基本的な打刻手順を説明します。","source":"@site/docs/staff/time-recording.md","sourceDirName":"staff","slug":"/staff/time-recording","permalink":"/docs/staff/time-recording","draft":false,"unlisted":false,"tags":[],"version":"current","sidebarPosition":3,"frontMatter":{"sidebar_position":3},"sidebar":"mainSidebar","previous":{"title":"基本操作","permalink":"/docs/staff/basic-operations"},"next":{"title":"打刻ダッシュボードを確認する","permalink":"/docs/staff/dashboard"}},{"id":"staff/workflow","title":"ワークフロー申請を操作する","description":"申請の作成、提出、確認、再提出の手順です。","source":"@site/docs/staff/workflow.md","sourceDirName":"staff","slug":"/staff/workflow","permalink":"/docs/staff/workflow","draft":false,"unlisted":false,"tags":[],"version":"current","sidebarPosition":5,"frontMatter":{"sidebar_position":5},"sidebar":"mainSidebar","previous":{"title":"勤怠を確認する","permalink":"/docs/staff/attendance-check"},"next":{"title":"勤怠を修正する","permalink":"/docs/staff/attendance-edit"}}],"drafts":[],"sidebars":{"mainSidebar":[{"type":"doc","id":"intro"},{"type":"category","label":"スタッフ向け","items":[{"type":"doc","id":"staff/overview"},{"type":"doc","id":"staff/navigation-map"},{"type":"category","label":"基本操作","items":[{"type":"doc","id":"staff/basic-operations"},{"type":"doc","id":"staff/time-recording"},{"type":"doc","id":"staff/dashboard"},{"type":"doc","id":"staff/shift"},{"type":"doc","id":"staff/attendance-check"},{"type":"doc","id":"staff/workflow"},{"type":"doc","id":"staff/attendance-edit"},{"type":"doc","id":"staff/attendance-report"},{"type":"doc","id":"staff/request-check"}],"collapsed":true,"collapsible":true},{"type":"doc","id":"staff/faq"}],"collapsed":true,"collapsible":true},{"type":"category","label":"管理者向け","items":[{"type":"doc","id":"admin/overview"},{"type":"doc","id":"admin/navigation-map"},{"type":"category","label":"管理業務","items":[{"type":"doc","id":"admin/dashboard"},{"type":"doc","id":"admin/admin-shift"},{"type":"doc","id":"admin/shift-plan"},{"type":"doc","id":"admin/attendance-management"},{"type":"doc","id":"admin/daily-report"},{"type":"doc","id":"admin/attendances"},{"type":"doc","id":"admin/request-approval"},{"type":"doc","id":"admin/workflow"},{"type":"doc","id":"admin/operation-logs"},{"type":"doc","id":"admin/settings-management"},{"type":"doc","id":"admin/staff-management"}],"collapsed":true,"collapsible":true},{"type":"doc","id":"admin/faq"}],"collapsed":true,"collapsible":true},{"type":"category","label":"開発者向け","items":[{"type":"doc","id":"developer/overview"},{"type":"doc","id":"developer/getting-started/setup"},{"type":"doc","id":"developer/attendance-management-enabled"},{"type":"doc","id":"developer/attendance-error-list-display"},{"type":"doc","id":"developer/attendance-status-determination"}],"collapsed":true,"collapsible":true}]}}]}},"docusaurus-plugin-content-pages":{"default":[{"type":"jsx","permalink":"/","source":"@site/src/pages/index.tsx"},{"type":"mdx","permalink":"/markdown-page","source":"@site/src/pages/markdown-page.md","title":"Markdown page example","description":"You don't need React to write simple standalone pages.","frontMatter":{"title":"Markdown page example"},"unlisted":false}]},"docusaurus-plugin-debug":{},"docusaurus-plugin-svgr":{},"docusaurus-theme-classic":{},"docusaurus-theme-mermaid":{},"docusaurus-bootstrap-plugin":{},"docusaurus-mdx-fallback-plugin":{}}}