{"version":{"pluginId":"default","version":"current","label":"Next","banner":null,"badge":false,"noIndex":false,"className":"docs-version-current","isLast":true,"docsSidebars":{"mainSidebar":[{"type":"link","href":"/docs/intro","label":"はじめに","docId":"intro","unlisted":false},{"type":"category","label":"スタッフ向け","items":[{"type":"link","href":"/docs/staff/overview","label":"スタッフ向けドキュメント","docId":"staff/overview","unlisted":false},{"type":"link","href":"/docs/staff/navigation-map","label":"画面遷移マップ（スタッフ向け）","docId":"staff/navigation-map","unlisted":false},{"type":"category","label":"基本操作","items":[{"type":"link","href":"/docs/staff/basic-operations","label":"基本操作","docId":"staff/basic-operations","unlisted":false},{"type":"link","href":"/docs/staff/time-recording","label":"出退勤を打刻する","docId":"staff/time-recording","unlisted":false},{"type":"link","href":"/docs/staff/dashboard","label":"打刻ダッシュボードを確認する","docId":"staff/dashboard","unlisted":false},{"type":"link","href":"/docs/staff/shift","label":"シフトを確認・編集する","docId":"staff/shift","unlisted":false},{"type":"link","href":"/docs/staff/attendance-check","label":"勤怠を確認する","docId":"staff/attendance-check","unlisted":false},{"type":"link","href":"/docs/staff/workflow","label":"ワークフロー申請を操作する","docId":"staff/workflow","unlisted":false},{"type":"link","href":"/docs/staff/attendance-edit","label":"勤怠を修正する","docId":"staff/attendance-edit","unlisted":false},{"type":"link","href":"/docs/staff/attendance-report","label":"日報を記録する","docId":"staff/attendance-report","unlisted":false},{"type":"link","href":"/docs/staff/request-check","label":"申請を確認する","docId":"staff/request-check","unlisted":false}],"collapsed":true,"collapsible":true},{"type":"link","href":"/docs/staff/faq","label":"よくある質問","docId":"staff/faq","unlisted":false}],"collapsed":true,"collapsible":true},{"type":"category","label":"管理者向け","items":[{"type":"link","href":"/docs/admin/overview","label":"管理者向けドキュメント","docId":"admin/overview","unlisted":false},{"type":"link","href":"/docs/admin/navigation-map","label":"画面遷移マップ（管理者向け）","docId":"admin/navigation-map","unlisted":false},{"type":"category","label":"管理業務","items":[{"type":"link","href":"/docs/admin/dashboard","label":"ダッシュボードを確認する","docId":"admin/dashboard","unlisted":false},{"type":"link","href":"/docs/admin/admin-shift","label":"シフトを管理する","docId":"admin/admin-shift","unlisted":false},{"type":"link","href":"/docs/admin/shift-plan","label":"シフト計画を作成する","docId":"admin/shift-plan","unlisted":false},{"type":"link","href":"/docs/admin/attendance-management","label":"勤怠を管理する","docId":"admin/attendance-management","unlisted":false},{"type":"link","href":"/docs/admin/daily-report","label":"日報を管理する","docId":"admin/daily-report","unlisted":false},{"type":"link","href":"/docs/admin/attendances","label":"勤怠一覧を確認する","docId":"admin/attendances","unlisted":false},{"type":"link","href":"/docs/admin/request-approval","label":"申請を承認する","docId":"admin/request-approval","unlisted":false},{"type":"link","href":"/docs/admin/workflow","label":"ワークフロー申請を管理する","docId":"admin/workflow","unlisted":false},{"type":"link","href":"/docs/admin/operation-logs","label":"操作ログを確認する","docId":"admin/operation-logs","unlisted":false},{"type":"link","href":"/docs/admin/settings-management","label":"設定画面を管理する","docId":"admin/settings-management","unlisted":false},{"type":"link","href":"/docs/admin/staff-management","label":"スタッフを管理する","docId":"admin/staff-management","unlisted":false}],"collapsed":true,"collapsible":true},{"type":"link","href":"/docs/admin/faq","label":"よくある質問","docId":"admin/faq","unlisted":false}],"collapsed":true,"collapsible":true},{"type":"category","label":"開発者向け","items":[{"type":"link","href":"/docs/developer/overview","label":"開発者向けドキュメント","docId":"developer/overview","unlisted":false},{"type":"link","href":"/docs/developer/getting-started/setup","label":"セットアップ","docId":"developer/getting-started/setup","unlisted":false},{"type":"link","href":"/docs/developer/attendance-management-enabled","label":"勤怠管理対象フラグ仕様","docId":"developer/attendance-management-enabled","unlisted":false},{"type":"link","href":"/docs/developer/attendance-error-list-display","label":"打刻エラー一覧の表示仕様","docId":"developer/attendance-error-list-display","unlisted":false},{"type":"link","href":"/docs/developer/attendance-status-determination","label":"勤怠ステータス判定ロジック","docId":"developer/attendance-status-determination","unlisted":false}],"collapsed":true,"collapsible":true}]},"docs":{"admin/admin-shift":{"id":"admin/admin-shift","title":"シフトを管理する","description":"このページでは、シフトを確認、調整するための基本運用を説明します。","sidebar":"mainSidebar"},"admin/attendance-management":{"id":"admin/attendance-management","title":"勤怠を管理する","description":"このページでは、管理者が日々の勤怠状況を確認し、要確認データを解消する手順を説明します。","sidebar":"mainSidebar"},"admin/attendances":{"id":"admin/attendances","title":"勤怠一覧を確認する","description":"このページでは、勤怠一覧で優先度をつけて対応する手順を説明します。","sidebar":"mainSidebar"},"admin/daily-report":{"id":"admin/daily-report","title":"日報を管理する","description":"このページでは、スタッフの日報を確認して、未対応を減らす手順を説明します。","sidebar":"mainSidebar"},"admin/dashboard":{"id":"admin/dashboard","title":"ダッシュボードを確認する","description":"このページでは、管理画面ダッシュボード（/admin）でその日の優先対応を素早く判断するための見方を説明します。","sidebar":"mainSidebar"},"admin/faq":{"id":"admin/faq","title":"よくある質問","description":"Q. 管理者はどこで申請を確認できますか？","sidebar":"mainSidebar"},"admin/navigation-map":{"id":"admin/navigation-map","title":"画面遷移マップ（管理者向け）","description":"迷ったときに、目的から行き先を決めるためのページです。","sidebar":"mainSidebar"},"admin/operation-logs":{"id":"admin/operation-logs","title":"操作ログを確認する","description":"このページでは、いつ、誰が、どの操作をしたかを確認する手順を説明します。","sidebar":"mainSidebar"},"admin/overview":{"id":"admin/overview","title":"管理者向けドキュメント","description":"このセクションは、管理者の日常運用に必要な操作をまとめた案内です。","sidebar":"mainSidebar"},"admin/request-approval":{"id":"admin/request-approval","title":"申請を承認する","description":"このページでは、管理者が勤怠修正申請を確認し、承認・却下する手順を説明します。","sidebar":"mainSidebar"},"admin/settings-management":{"id":"admin/settings-management","title":"設定画面を管理する","description":"このページでは、管理者が設定画面で何を見直し、変更後にどこを確認すればよいかを説明します。","sidebar":"mainSidebar"},"admin/shift-plan":{"id":"admin/shift-plan","title":"シフト計画を作成する","description":"このページでは、年間のシフト計画を作成、更新するための基本運用を説明します。","sidebar":"mainSidebar"},"admin/staff-management":{"id":"admin/staff-management","title":"スタッフを管理する","description":"このページでは、スタッフアカウントを管理する手順を説明します。","sidebar":"mainSidebar"},"admin/workflow":{"id":"admin/workflow","title":"ワークフロー申請を管理する","description":"このページでは、管理者がワークフロー画面で申請を確認し、承認・却下を行う手順を説明します。","sidebar":"mainSidebar"},"developer/attendance-error-list-display":{"id":"developer/attendance-error-list-display","title":"打刻エラー一覧の表示仕様","description":"/attendance/list のデスクトップ画面に表示される「打刻エラー一覧」と、モバイル画面の警告アラートの表示条件を定義する。","sidebar":"mainSidebar"},"developer/attendance-management-enabled":{"id":"developer/attendance-management-enabled","title":"勤怠管理対象フラグ仕様","description":"このページは、スタッフ単位の勤怠管理対象フラグ（attendanceManagementEnabled）の仕様をまとめる。","sidebar":"mainSidebar"},"developer/attendance-status-determination":{"id":"developer/attendance-status-determination","title":"勤怠ステータス判定ロジック","description":"スタッフの 1 日分の勤怠ステータスを返す中核ライブラリの仕様を定義する。","sidebar":"mainSidebar"},"developer/getting-started/setup":{"id":"developer/getting-started/setup","title":"セットアップ","description":"このページは、garaku-frontend の開発を始めるための最小セットアップ手順です。","sidebar":"mainSidebar"},"developer/overview":{"id":"developer/overview","title":"開発者向けドキュメント","description":"このセクションは、garaku-frontend の開発に参加するメンバー向けです。","sidebar":"mainSidebar"},"intro":{"id":"intro","title":"はじめに","description":"このサイトは、garaku-frontend のドキュメントポータルです。","sidebar":"mainSidebar"},"staff/attendance-check":{"id":"staff/attendance-check","title":"勤怠を確認する","description":"このページでは、打刻後の勤怠確認と、必要時の修正申請の流れを説明します。","sidebar":"mainSidebar"},"staff/attendance-edit":{"id":"staff/attendance-edit","title":"勤怠を修正する","description":"このページでは、勤怠編集画面で打刻ミスや休憩漏れを修正し、申請する手順を説明します。","sidebar":"mainSidebar"},"staff/attendance-report":{"id":"staff/attendance-report","title":"日報を記録する","description":"このページでは、日報画面でその日の業務内容を記録し、提出する手順を説明します。","sidebar":"mainSidebar"},"staff/basic-operations":{"id":"staff/basic-operations","title":"基本操作","description":"このページでは、日常業務でよく使う操作を、最短で確認できるようにまとめます。","sidebar":"mainSidebar"},"staff/dashboard":{"id":"staff/dashboard","title":"打刻ダッシュボードを確認する","description":"このページでは、打刻画面の右側に表示される「打刻ダッシュボード」で何を確認できるかを説明します。","sidebar":"mainSidebar"},"staff/faq":{"id":"staff/faq","title":"よくある質問","description":"Q. どこから始めればよいですか？","sidebar":"mainSidebar"},"staff/navigation-map":{"id":"staff/navigation-map","title":"画面遷移マップ（スタッフ向け）","description":"迷ったときに、目的から行き先を決めるためのページです。","sidebar":"mainSidebar"},"staff/overview":{"id":"staff/overview","title":"スタッフ向けドキュメント","description":"このセクションは、日々の勤怠作業を行うスタッフ向けの案内です。","sidebar":"mainSidebar"},"staff/request-check":{"id":"staff/request-check","title":"申請を確認する","description":"このページでは、勤怠修正申請の確認手順を説明します。","sidebar":"mainSidebar"},"staff/shift":{"id":"staff/shift","title":"シフトを確認・編集する","description":"このページでは、シフトの確認と編集の基本操作を説明します。","sidebar":"mainSidebar"},"staff/time-recording":{"id":"staff/time-recording","title":"出退勤を打刻する","description":"このページでは、勤務開始から勤務終了までの基本的な打刻手順を説明します。","sidebar":"mainSidebar"},"staff/workflow":{"id":"staff/workflow","title":"ワークフロー申請を操作する","description":"申請の作成、提出、確認、再提出の手順です。","sidebar":"mainSidebar"}}}}